README.rst
setup.py
latex/__init__.py
latex/build.py
latex/exc.py
latex/jinja2.py
latex.egg-info/PKG-INFO
latex.egg-info/SOURCES.txt
latex.egg-info/dependency_links.txt
latex.egg-info/requires.txt
latex.egg-info/top_level.txt