Metadata-Version: 1.0
Name: latex
Version: 0.5.4
Summary: Wrappers for calling LaTeX/building LaTeX documents.
Home-page: http://github.com/mbr/latex
Author: Marc Brinkmann
Author-email: git@marcbrinkmann.de
License: MIT
Platform: UNKNOWN
